MANIFEST.in
ligo-lvalert-heartbeat.spec
setup.cfg
setup.py
bin/lvalert_heartbeat-client
bin/lvalert_heartbeat-server
debian/changelog
debian/compat
debian/control
debian/copyright
debian/rules
debian/source/format
ligo/__init__.py
ligo/lvalert_heartbeat/__init__.py
ligo/lvalert_heartbeat/lvalertMP_heartbeat.py
ligo/lvalert_heartbeat/lvalert_heartbeat.py
ligo_lvalert_heartbeat.egg-info/PKG-INFO
ligo_lvalert_heartbeat.egg-info/SOURCES.txt
ligo_lvalert_heartbeat.egg-info/dependency_links.txt
ligo_lvalert_heartbeat.egg-info/requires.txt
ligo_lvalert_heartbeat.egg-info/top_level.txt