Metadata-Version: 1.0
Name: ligo-lvalert-heartbeat
Version: 1.1
Summary: a monitor to ensure lvalert listeners are responding to alerts
Home-page: UNKNOWN
Author: Reed Essick
Author-email: reed.essick@ligo.org
License: GNU General Public License Version 3
Platform: UNKNOWN
